picturebot/__init__.py
picturebot/base.py
picturebot/cli.py
picturebot/cli_OLD.py
picturebot/config.json
picturebot/directory.py
picturebot/flow.py
picturebot/helper.py
picturebot/poco.py
picturebot/shoot.py
picturebot/workspace.py
picturebot-0.0.18.dist-info/AUTHORS.rst
picturebot-0.0.18.dist-info/LICENSE
picturebot-0.0.18.dist-info/METADATA
picturebot-0.0.18.dist-info/WHEEL
picturebot-0.0.18.dist-info/entry_points.txt
picturebot-0.0.18.dist-info/top_level.txt
picturebot-0.0.18.dist-info/RECORD
