Metadata-Version: 2.1
Name: picturebot
Version: 0.0.18
Summary: Program to ease picture development flow 
Home-page: https://github.com/Tomekske/picturebot
Author: Tomek Joostens
Author-email: joostenstomek@gmail.com
License: MIT license
Keywords: picturebot
Platform: UNKNOWN
Classifier: Development Status :: 2 - Pre-Alpha
Classifier: Intended Audience :: Developers
Classifier: License :: OSI Approved :: MIT License
Classifier: Natural Language :: English
Classifier: Programming Language :: Python :: 3
Classifier: Programming Language :: Python :: 3.7
Requires-Dist: Click (>=6.0)
Requires-Dist: generalutils
